LICENSE
MANIFEST.in
README.rst
config.cnf
setup.py
bin/pdfebc-web
bin/pdfebc-web-start-celery-redis
pdfebc_web/__init__.py
pdfebc_web/factory.py
pdfebc_web/startapp.py
pdfebc_web.egg-info/PKG-INFO
pdfebc_web.egg-info/SOURCES.txt
pdfebc_web.egg-info/dependency_links.txt
pdfebc_web.egg-info/not-zip-safe
pdfebc_web.egg-info/requires.txt
pdfebc_web.egg-info/top_level.txt
pdfebc_web/main/__init__.py
pdfebc_web/main/forms.py
pdfebc_web/main/views.py
pdfebc_web/static/style.css
pdfebc_web/templates/about.html
pdfebc_web/templates/base.html
pdfebc_web/templates/index.html
pdfebc_web/util/__init__.py
pdfebc_web/util/file.py