Metadata-Version: 1.1
Name: pdfebc-web
Version: 0.1.2
Summary: Web interface for pdfebc.
Home-page: https://github.com/slarse/pdfebc-web
Author: Simon Larsén
Author-email: slarse@kth.se
License: MIT License
